[
  {
    "rank": 1,
    "points": 7,
    "matchesPlayed": 3,
    "matchesWon": 2,
    "matchesDrawn": 1,
    "matchesLost": 0,
    "goalsFor": 3,
    "goalsAgainst": 1,
    "goalDifference": 2,
    "team": {
      "id": "Belgrano",
      "color": "#0598D1",
      "name": "Belgrano",
      "shortName": "BEL",
      "image": "https://lbdtw-api.bustosluciano89.workers.dev/static/logos/Belgrano.png"
    }
  },
  {
    "rank": 2,
    "points": 7,
    "matchesPlayed": 3,
    "matchesWon": 2,
    "matchesDrawn": 1,
    "matchesLost": 0,
    "goalsFor": 2,
    "goalsAgainst": 0,
    "goalDifference": 2,
    "team": {
      "id": "Godoy-Cruz",
      "color": "#014e7c",
      "name": "Godoy Cruz",
      "shortName": "GCM",
      "image": "https://lbdtw-api.bustosluciano89.workers.dev/static/logos/Godoy-Cruz.png"
    }
  },
  {
    "rank": 3,
    "points": 6,
    "matchesPlayed": 2,
    "matchesWon": 2,
    "matchesDrawn": 0,
    "matchesLost": 0,
    "goalsFor": 7,
    "goalsAgainst": 4,
    "goalDifference": 3,
    "team": {
      "id": "Huracan",
      "color": "#ae0407",
      "name": "Huracan",
      "shortName": "HUR",
      "image": "https://lbdtw-api.bustosluciano89.workers.dev/static/logos/Huracan.png"
    }
  },
  {
    "rank": 4,
    "points": 6,
    "matchesPlayed": 2,
    "matchesWon": 2,
    "matchesDrawn": 0,
    "matchesLost": 0,
    "goalsFor": 4,
    "goalsAgainst": 2,
    "goalDifference": 2,
    "team": {
      "id": "Lanus",
      "color": "#6f1c28",
      "name": "Lanus",
      "shortName": "LAN",
      "image": "https://lbdtw-api.bustosluciano89.workers.dev/static/logos/Lanus.png"
    }
  },
  {
    "rank": 5,
    "points": 5,
    "matchesPlayed": 3,
    "matchesWon": 1,
    "matchesDrawn": 2,
    "matchesLost": 0,
    "goalsFor": 3,
    "goalsAgainst": 2,
    "goalDifference": 1,
    "team": {
      "id": "Newells",
      "color": "#eb1921",
      "name": "Newells",
      "shortName": "NOB",
      "image": "https://lbdtw-api.bustosluciano89.workers.dev/static/logos/Newells.png"
    }
  },
  {
    "rank": 6,
    "points": 4,
    "matchesPlayed": 2,
    "matchesWon": 1,
    "matchesDrawn": 1,
    "matchesLost": 0,
    "goalsFor": 2,
    "goalsAgainst": 0,
    "goalDifference": 2,
    "team": {
      "id": "Instituto",
      "color": "#e72428",
      "name": "Instituto",
      "shortName": "IACC",
      "image": "https://lbdtw-api.bustosluciano89.workers.dev/static/logos/Instituto.png"
    }
  },
  {
    "rank": 7,
    "points": 4,
    "matchesPlayed": 2,
    "matchesWon": 1,
    "matchesDrawn": 1,
    "matchesLost": 0,
    "goalsFor": 4,
    "goalsAgainst": 3,
    "goalDifference": 1,
    "team": {
      "id": "Platense",
      "color": "#2a1608",
      "name": "Platense",
      "shortName": "PLA",
      "image": "https://lbdtw-api.bustosluciano89.workers.dev/static/logos/Platense.png"
    }
  },
  {
    "rank": 8,
    "points": 4,
    "matchesPlayed": 2,
    "matchesWon": 1,
    "matchesDrawn": 1,
    "matchesLost": 0,
    "goalsFor": 4,
    "goalsAgainst": 3,
    "goalDifference": 1,
    "team": {
      "id": "Tigre",
      "color": "#18347c",
      "name": "Tigre",
      "shortName": "TIG",
      "image": "https://lbdtw-api.bustosluciano89.workers.dev/static/logos/Tigre.png"
    }
  },
  {
    "rank": 9,
    "points": 4,
    "matchesPlayed": 2,
    "matchesWon": 1,
    "matchesDrawn": 1,
    "matchesLost": 0,
    "goalsFor": 3,
    "goalsAgainst": 2,
    "goalDifference": 1,
    "team": {
      "id": "Rosario-Central",
      "color": "#ffc40c",
      "name": "Rosario Central",
      "shortName": "ROS",
      "image": "https://lbdtw-api.bustosluciano89.workers.dev/static/logos/Rosario-Central.png"
    }
  },
  {
    "rank": 10,
    "points": 4,
    "matchesPlayed": 2,
    "matchesWon": 1,
    "matchesDrawn": 1,
    "matchesLost": 0,
    "goalsFor": 1,
    "goalsAgainst": 0,
    "goalDifference": 1,
    "team": {
      "id": "Boca-Juniors",
      "color": "#12386d",
      "name": "Boca Juniors",
      "shortName": "CABJ",
      "image": "https://lbdtw-api.bustosluciano89.workers.dev/static/logos/Boca.png"
    }
  },
  {
    "rank": 11,
    "points": 4,
    "matchesPlayed": 3,
    "matchesWon": 1,
    "matchesDrawn": 1,
    "matchesLost": 1,
    "goalsFor": 5,
    "goalsAgainst": 5,
    "goalDifference": 0,
    "team": {
      "id": "Sarmiento",
      "color": "#06a43f",
      "name": "Sarmiento (J)",
      "shortName": "SARM",
      "image": "https://lbdtw-api.bustosluciano89.workers.dev/static/logos/Sarmiento.png"
    }
  },
  {
    "rank": 12,
    "points": 4,
    "matchesPlayed": 3,
    "matchesWon": 1,
    "matchesDrawn": 1,
    "matchesLost": 1,
    "goalsFor": 4,
    "goalsAgainst": 4,
    "goalDifference": 0,
    "team": {
      "id": "Defensa-y-Justicia",
      "color": "#ffdd02",
      "name": "Def y Justicia",
      "shortName": "DYJ",
      "image": "https://lbdtw-api.bustosluciano89.workers.dev/static/logos/Defensa-y-Justicia.png"
    }
  },
  {
    "rank": 13,
    "points": 4,
    "matchesPlayed": 3,
    "matchesWon": 1,
    "matchesDrawn": 1,
    "matchesLost": 1,
    "goalsFor": 2,
    "goalsAgainst": 2,
    "goalDifference": 0,
    "team": {
      "id": "San-Lorenzo",
      "color": "#dd2b2f",
      "name": "San Lorenzo",
      "shortName": "SL",
      "image": "https://lbdtw-api.bustosluciano89.workers.dev/static/logos/San-Lorenzo.png"
    }
  },
  {
    "rank": 14,
    "points": 3,
    "matchesPlayed": 2,
    "matchesWon": 1,
    "matchesDrawn": 0,
    "matchesLost": 1,
    "goalsFor": 5,
    "goalsAgainst": 4,
    "goalDifference": 1,
    "team": {
      "id": "Barracas-Central",
      "color": "#ea2f2f",
      "name": "Barracas Central",
      "shortName": "BAR",
      "image": "https://lbdtw-api.bustosluciano89.workers.dev/static/logos/Barracas-Central.png"
    }
  },
  {
    "rank": 15,
    "points": 3,
    "matchesPlayed": 2,
    "matchesWon": 1,
    "matchesDrawn": 0,
    "matchesLost": 1,
    "goalsFor": 3,
    "goalsAgainst": 2,
    "goalDifference": 1,
    "team": {
      "id": "River-Plate",
      "color": "#df1e19",
      "name": "River Plate",
      "shortName": "CARP",
      "image": "https://lbdtw-api.bustosluciano89.workers.dev/static/logos/River.png"
    }
  },
  {
    "rank": 16,
    "points": 3,
    "matchesPlayed": 2,
    "matchesWon": 1,
    "matchesDrawn": 0,
    "matchesLost": 1,
    "goalsFor": 3,
    "goalsAgainst": 2,
    "goalDifference": 1,
    "team": {
      "id": "Velez",
      "color": "#85c7fc",
      "name": "Velez",
      "shortName": "VEL",
      "image": "https://lbdtw-api.bustosluciano89.workers.dev/static/logos/Velez.png"
    }
  },
  {
    "rank": 17,
    "points": 3,
    "matchesPlayed": 2,
    "matchesWon": 1,
    "matchesDrawn": 0,
    "matchesLost": 1,
    "goalsFor": 2,
    "goalsAgainst": 1,
    "goalDifference": 1,
    "team": {
      "id": "Talleres",
      "color": "#2957bf",
      "name": "Talleres (C)",
      "shortName": "TDC",
      "image": "https://lbdtw-api.bustosluciano89.workers.dev/static/logos/Talleres.png"
    }
  },
  {
    "rank": 18,
    "points": 3,
    "matchesPlayed": 2,
    "matchesWon": 1,
    "matchesDrawn": 0,
    "matchesLost": 1,
    "goalsFor": 2,
    "goalsAgainst": 2,
    "goalDifference": 0,
    "team": {
      "id": "Independiente",
      "color": "#de0019",
      "name": "Independiente",
      "shortName": "IND",
      "image": "https://lbdtw-api.bustosluciano89.workers.dev/static/logos/Independiente.png"
    }
  },
  {
    "rank": 19,
    "points": 3,
    "matchesPlayed": 2,
    "matchesWon": 1,
    "matchesDrawn": 0,
    "matchesLost": 1,
    "goalsFor": 1,
    "goalsAgainst": 1,
    "goalDifference": 0,
    "team": {
      "id": "Argentinos",
      "color": "#e8272b",
      "name": "Argentinos",
      "shortName": "ARGJ",
      "image": "https://lbdtw-api.bustosluciano89.workers.dev/static/logos/Argentinos.png"
    }
  },
  {
    "rank": 20,
    "points": 1,
    "matchesPlayed": 2,
    "matchesWon": 0,
    "matchesDrawn": 1,
    "matchesLost": 1,
    "goalsFor": 2,
    "goalsAgainst": 3,
    "goalDifference": -1,
    "team": {
      "id": "Banfield",
      "color": "#81f1a9",
      "name": "Banfield",
      "shortName": "BAN",
      "image": "https://lbdtw-api.bustosluciano89.workers.dev/static/logos/Banfield.png"
    }
  },
  {
    "rank": 21,
    "points": 1,
    "matchesPlayed": 2,
    "matchesWon": 0,
    "matchesDrawn": 1,
    "matchesLost": 1,
    "goalsFor": 2,
    "goalsAgainst": 3,
    "goalDifference": -1,
    "team": {
      "id": "Estudiantes",
      "color": "#ea1921",
      "name": "Estudiantes (LP)",
      "shortName": "EST",
      "image": "https://lbdtw-api.bustosluciano89.workers.dev/static/logos/Estudiantes.png"
    }
  },
  {
    "rank": 22,
    "points": 1,
    "matchesPlayed": 2,
    "matchesWon": 0,
    "matchesDrawn": 1,
    "matchesLost": 1,
    "goalsFor": 1,
    "goalsAgainst": 2,
    "goalDifference": -1,
    "team": {
      "id": "Arsenal",
      "color": "#ac110b",
      "name": "Arsenal",
      "shortName": "ARS",
      "image": "https://lbdtw-api.bustosluciano89.workers.dev/static/logos/Arsenal.png"
    }
  },
  {
    "rank": 23,
    "points": 1,
    "matchesPlayed": 2,
    "matchesWon": 0,
    "matchesDrawn": 1,
    "matchesLost": 1,
    "goalsFor": 0,
    "goalsAgainst": 1,
    "goalDifference": -1,
    "team": {
      "id": "Racing-Club",
      "color": "#6ccbf9",
      "name": "Racing Club",
      "shortName": "RAC",
      "image": "https://lbdtw-api.bustosluciano89.workers.dev/static/logos/Racing-Club.png"
    }
  },
  {
    "rank": 24,
    "points": 1,
    "matchesPlayed": 2,
    "matchesWon": 0,
    "matchesDrawn": 1,
    "matchesLost": 1,
    "goalsFor": 0,
    "goalsAgainst": 2,
    "goalDifference": -2,
    "team": {
      "id": "Union",
      "color": "#ec1a21",
      "name": "Union",
      "shortName": "USF",
      "image": "https://lbdtw-api.bustosluciano89.workers.dev/static/logos/Union.png"
    }
  },
  {
    "rank": 25,
    "points": 1,
    "matchesPlayed": 3,
    "matchesWon": 0,
    "matchesDrawn": 1,
    "matchesLost": 2,
    "goalsFor": 0,
    "goalsAgainst": 3,
    "goalDifference": -3,
    "team": {
      "id": "Central-Cordoba",
      "color": "#000",
      "name": "Central Cba (SdE)",
      "shortName": "CSE",
      "image": "https://lbdtw-api.bustosluciano89.workers.dev/static/logos/Central-Cordoba.png"
    }
  },
  {
    "rank": 26,
    "points": 0,
    "matchesPlayed": 2,
    "matchesWon": 0,
    "matchesDrawn": 0,
    "matchesLost": 2,
    "goalsFor": 0,
    "goalsAgainst": 3,
    "goalDifference": -3,
    "team": {
      "id": "Atlético-Tucumán",
      "color": "#83baee",
      "name": "Atl Tucuman",
      "shortName": "TUC",
      "image": "https://lbdtw-api.bustosluciano89.workers.dev/static/logos/Atletico-Tucuman.png"
    }
  },
  {
    "rank": 27,
    "points": 0,
    "matchesPlayed": 3,
    "matchesWon": 0,
    "matchesDrawn": 0,
    "matchesLost": 3,
    "goalsFor": 1,
    "goalsAgainst": 5,
    "goalDifference": -4,
    "team": {
      "id": "Colon",
      "color": "#fa555a",
      "name": "Colon",
      "shortName": "COL",
      "image": "https://lbdtw-api.bustosluciano89.workers.dev/static/logos/Colon.png"
    }
  },
  {
    "rank": 28,
    "points": 0,
    "matchesPlayed": 2,
    "matchesWon": 0,
    "matchesDrawn": 0,
    "matchesLost": 2,
    "goalsFor": 1,
    "goalsAgainst": 5,
    "goalDifference": -4,
    "team": {
      "id": "Gimnasia",
      "color": "#6370fc",
      "name": "Gimnasia (LP)",
      "shortName": "GLP",
      "image": "https://lbdtw-api.bustosluciano89.workers.dev/static/logos/Gimnasia-La-Plata.png"
    }
  }
]