[
  {
    "competition": "Premier League",
    "matches": [
      {
        "hour": "26' ",
        "teams": [
          {
            "localImgId": "1373.png",
            "name": "Brentford",
            "localScore": "1"
          },
          {
            "visitantImgId": "780.png",
            "name": "Wolverhampton",
            "visitantScore": "2"
          }
        ]
      },
      {
        "hour": "27' ",
        "teams": [
          {
            "localImgId": "531.png",
            "name": "Chelsea",
            "localScore": "1"
          },
          {
            "visitantImgId": "621.png",
            "name": "Crystal Palace",
            "visitantScore": "0"
          }
        ]
      },
      {
        "hour": "17:15  ",
        "teams": [
          {
            "localImgId": "532.png",
            "name": "Everton",
            "localScore": ""
          },
          {
            "visitantImgId": "535.png",
            "name": "Manchester City",
            "visitantScore": ""
          }
        ]
      }
    ]
  }
]