[
  {
    "competition": "Copa De La Liga",
    "matches": [
      {
        "hour": "Final",
        "teams": [
          {
            "localImgId": "20.png",
            "name": {
              "id": "Tigre",
              "color": "#1E448D",
              "colorSecondary": "#ED2A3C",
              "name": "Tigre",
              "shortName": "TIG",
              "image": "https://api.lbdtwplus.com.ar/static/logos/Tigre.svg",
              "imageWhite": "https://api.lbdtwplus.com.ar/static/logos/Tigre-white.svg",
              "league": "LPF"
            },
            "localScore": "0"
          },
          {
            "visitantImgId": "14.png",
            "name": {
              "id": "Newells",
              "color": "#ED1C24",
              "colorSecondary": "#000000",
              "name": "Newells",
              "shortName": "NOB",
              "image": "https://api.lbdtwplus.com.ar/static/logos/Newells.svg",
              "imageWhite": "https://api.lbdtwplus.com.ar/static/logos/Newells-white.svg",
              "league": "LPF"
            },
            "visitantScore": "2"
          }
        ]
      },
      {
        "hour": "Final",
        "teams": [
          {
            "localImgId": "11.png",
            "name": {
              "id": "Huracan",
              "color": "#FF0000",
              "colorSecondary": "#FFFFFF",
              "name": "Huracan",
              "shortName": "HUR",
              "image": "https://api.lbdtwplus.com.ar/static/logos/Huracan.svg",
              "imageWhite": "https://api.lbdtwplus.com.ar/static/logos/Huracan-white.svg",
              "league": "LPF"
            },
            "localScore": "1"
          },
          {
            "visitantImgId": "33.png",
            "name": {
              "id": "Instituto",
              "color": "#E0312B",
              "colorSecondary": "#FFFFFF",
              "name": "Instituto",
              "shortName": "IACC",
              "image": "https://api.lbdtwplus.com.ar/static/logos/Instituto.svg",
              "imageWhite": "https://api.lbdtwplus.com.ar/static/logos/Instituto-white.svg",
              "league": "LPF"
            },
            "visitantScore": "3"
          }
        ]
      },
      {
        "hour": "Final",
        "teams": [
          {
            "localImgId": "52.png",
            "name": {
              "id": "Talleres",
              "color": "#00184C",
              "colorSecondary": "#FFFFFF",
              "name": "Talleres (C)",
              "shortName": "CAT",
              "image": "https://api.lbdtwplus.com.ar/static/logos/Talleres.svg",
              "imageWhite": "https://api.lbdtwplus.com.ar/static/logos/Talleres-white.svg",
              "league": "LPF"
            },
            "localScore": "1"
          },
          {
            "visitantImgId": "4.png",
            "name": {
              "id": "Arsenal",
              "color": "#13B5EA",
              "colorSecondary": "#EF3340",
              "name": "Arsenal",
              "shortName": "ARS",
              "image": "https://api.lbdtwplus.com.ar/static/logos/Arsenal.svg",
              "imageWhite": "https://api.lbdtwplus.com.ar/static/logos/Arsenal-white.svg",
              "league": "LPF"
            },
            "visitantScore": "1"
          }
        ]
      },
      {
        "hour": "Final",
        "teams": [
          {
            "localImgId": "6.png",
            "name": {
              "id": "Boca",
              "color": "#023F86",
              "colorSecondary": "#F7A600",
              "name": "Boca Juniors",
              "shortName": "CABJ",
              "image": "https://api.lbdtwplus.com.ar/static/logos/Boca.svg",
              "imageWhite": "https://api.lbdtwplus.com.ar/static/logos/Boca-white.svg",
              "league": "LPF"
            },
            "localScore": "2"
          },
          {
            "visitantImgId": "39.png",
            "name": {
              "id": "Union",
              "color": "#DA251D",
              "colorSecondary": "#FFFFFF",
              "name": "Union",
              "shortName": "USF",
              "image": "https://api.lbdtwplus.com.ar/static/logos/Union.svg",
              "imageWhite": "https://api.lbdtwplus.com.ar/static/logos/Union-white.svg",
              "league": "LPF"
            },
            "visitantScore": "1"
          }
        ]
      }
    ]
  },
  {
    "competition": "La Liga",
    "matches": [
      {
        "hour": "Final",
        "teams": [
          {
            "localImgId": "511.png",
            "name": {
              "id": "Osasuna",
              "color": "#b4001d ",
              "colorSecondary": "#14213d",
              "name": "Osasuna",
              "shortName": "OSA",
              "image": "https://api.lbdtwplus.com.ar/static/logos/Osasuna.svg",
              "imageWhite": "https://api.lbdtwplus.com.ar/static/logos/Osasuna-white.svg",
              "league": "LaLiga"
            },
            "localScore": "2"
          },
          {
            "visitantImgId": "513.png",
            "name": {
              "id": "Granada",
              "color": "#002246",
              "colorSecondary": "#ffe715",
              "name": "Granada",
              "shortName": "GRN",
              "image": "https://api.lbdtwplus.com.ar/static/logos/Granada.svg",
              "imageWhite": "https://api.lbdtwplus.com.ar/static/logos/Granada-white.svg",
              "league": "LaLiga"
            },
            "visitantScore": "0"
          }
        ]
      }
    ]
  },
  {
    "competition": "Bundesliga",
    "matches": [
      {
        "hour": "Final",
        "teams": [
          {
            "localImgId": "603.png",
            "name": "B. Dortmund",
            "localScore": "1"
          },
          {
            "visitantImgId": "617.png",
            "name": "Werder Bremen",
            "visitantScore": "0"
          }
        ]
      }
    ]
  },
  {
    "competition": "Liga Francia",
    "matches": [
      {
        "hour": "Final",
        "teams": [
          {
            "localImgId": "1305.png",
            "name": "Le Havre",
            "localScore": "0"
          },
          {
            "visitantImgId": "642.png",
            "name": "Lens",
            "visitantScore": "0"
          }
        ]
      }
    ]
  },
  {
    "competition": "Liga Colombia",
    "matches": [
      {
        "hour": "Final",
        "teams": [
          {
            "localImgId": "1334.png",
            "name": "Envigado",
            "localScore": "3"
          },
          {
            "visitantImgId": "773.png",
            "name": "Dep. Cali",
            "visitantScore": "0"
          }
        ]
      },
      {
        "hour": "Final",
        "teams": [
          {
            "localImgId": "760.png",
            "name": "Jaguares (C)",
            "localScore": "1"
          },
          {
            "visitantImgId": "1030.png",
            "name": "Dep. Pasto",
            "visitantScore": "0"
          }
        ]
      },
      {
        "hour": "67' ",
        "teams": [
          {
            "localImgId": "881.png",
            "name": "La Equidad",
            "localScore": "1"
          },
          {
            "visitantImgId": "882.png",
            "name": "Rionegro A.",
            "visitantScore": "1"
          }
        ]
      }
    ]
  },
  {
    "competition": "Liga Paraguay",
    "matches": [
      {
        "hour": "Final",
        "teams": [
          {
            "localImgId": "719.png",
            "name": "Libertad (P)",
            "localScore": "3"
          },
          {
            "visitantImgId": "1702.png",
            "name": "Sp. Ameliano",
            "visitantScore": "0"
          }
        ]
      }
    ]
  },
  {
    "competition": "Liga Mexico",
    "matches": [
      {
        "hour": "87' ",
        "teams": [
          {
            "localImgId": "895.png",
            "name": "Atlas (G)",
            "localScore": "1"
          },
          {
            "visitantImgId": "1548.png",
            "name": "Mazatlan",
            "visitantScore": "2"
          }
        ]
      },
      {
        "hour": "80' ",
        "teams": [
          {
            "localImgId": "970.png",
            "name": "FC Juarez",
            "localScore": "0"
          },
          {
            "visitantImgId": "902.png",
            "name": "Pachuca",
            "visitantScore": "1"
          }
        ]
      }
    ]
  }
]